Workbook

Sheet 【重要】始めにお読みください
B1: 外部発表_広告表示チェックシート | E1: Ver.1.1 (2025/11/13)
B18: 外部発表の種別※ | D18: 使用するチェックシート | E18: (A)(B)どちらをチェックしたか”〇”を付けて下さい
B19: (A) | C19: 報道発表、TVCM、ラジオCM、新聞広告、雑誌広告、Web/SNS広告、チラシ/パンフレット、OOH（ポスター/交通広告/看板） 、展示会出展用広告 | D19: 「広告・宣伝用」チェックシート 「共通」チェックシート
B20: (B) | C20: 論文、技術投稿、出版、学会講演、技術解説（注） （注）イベント・セミナー、WEB上での発表含 | D20: 「論文・書籍・技術解説用 _総括表」チェックシート 「論文・書籍・技術解説用_個別確認」チェックシート 「共通」チェックシート | E20: 〇
C22: ※媒体を問いません（紙、WEB、HP、DVD等）
C24: 問合せ先：外部発表_広告表示チェックシート事前照会 | D24: （Form形式）

Sheet (A)広告・宣伝用
A1: 外部発表_広告表示チェックシート（広告・宣伝用）
H2: 45962
H3: 広報部門、営業推進部門、知財・輸出部門
B6: 基本情報
C7: 施策名 | N7: NTT
C8: 施策主管会社 | N8: NTTグリーン＆フード
C9: 施策主管組織 | N9: NTTソノリティ
C10: 原稿作成者 発表者
C11: チェック実施者 | E11: ※原稿作成者・発表者以外がチェック実施すること | N11: NTT AI-CIX
C12: 広告種別 | J12: FALSE | K12: FALSE | N12: NTTイノベーティブデバイス | Q12: OOH（ポスター/交通広告/看板）
D13: TVCM、新聞広告については持株広報部門へ事前照会をお願いします | N13: NTTプレシジョンメディシン
C14: 広告内容 | J14: FALSE | N14: NTTテクノクロス
J15: FALSE
J16: FALSE
B19: 1. ブランド観点
C20: 項番 | E20: はい | F20: いいえ | G20: 対象外 | H20: 補足・備考
C21: (1) | D21: 最新の「NTT / NTTグループ ブランドガイドライン」※を参照し、CI/GI規定、ブランドカラー、フォント、各種ロゴ等について、ガイドラインに沿った広告表現になっている ※ブランドガイドライン： https://nnn.gvm-jp.groupis-gn.ntt/jp/GI/ | J21: FALSE | K21: FALSE | L21: FALSE
C22: (2) | D22: 広告表現や施策によって目指すところが、自社のビジョンと矛盾していない | J22: FALSE | K22: FALSE | L22: FALSE
C23: (3) | D23: 事業環境を取り巻く状況を踏まえて適切なタイミングでの公開となっている （ネガティブなトレンドはないか） | J23: FALSE | K23: FALSE | L23: FALSE
D24: また、使用する製品名について知財部門に事前照会済である | E24: FALSE | F24: FALSE | G24: FALSE
C25: (4) | D25: （新たな）タレントを起用していない※ | H25: 写真素材のモデルは対象外とする | J25: FALSE | K25: FALSE | L25: FALSE
D26: ※公開範囲問わず、タレント起用をご検討の際は事前に持株会社 広報部門へご相談ください | H26: 持株会社 広報部門へは営業推進部広報部門から連絡する （計画段階で広報部門へ相談）
C27: (5) | D27: お客さまにとって分かりにくい専門用語はない （専門用語を用いている場合でも、用語の内容を説明している） | J27: FALSE | K27: FALSE | L27: FALSE
C28: (6) | D28: 差別的な表現、お客さまが不快感を抱くような表現、持株会社やNTTグループの品位を低下させるような表現等がない | J28: FALSE
C29: (7) | D29: あいまいな表現や、誤解を生む可能性がある表現等がない
C30: (8) | D30: 他社（者）や業界、業種を批判・否定するような表現になっていない
C31: (9) | D31: 全体を通し、ネガティブな表現になっていない
C32: (10) | D32: 事実よりも誇張した表現が含まれていない | J32: FALSE
C33: (11) | D33: 事実と関係性の低いビジュアルを用いていない （事実と関連がないのに、「子どもの笑顔」「豊かな自然」等の写真やイメージの付与を行わない※） ※子どもを広告に起用する場合は、「サステナビリティ・コミュニケーションガイド2023」 （2023年株式会社電通作成）のP50を参照 https://www.group.dentsu.com/jp/sustainability/pdf/sustainability-communication-guide2023.pdf | J33: FALSE | K33: FALSE
C34: (12) | D34: 数値を表示する場合、その数値の根拠や算出方法が明確に示されている
C35: (13) | D35: 表示する名称・スペックは全て正確に記載している | J35: FALSE
C36: (14) | D36: 掲載する情報は最新のものである、もしくは、変動がある情報については、いつ時点の情報か明示している
C37: (15) | D37: クリエイティブについて不具合があった場合、その修理/修復/賠償等の責任の所在は明確になっており、また、契約書等で合意がなされている | H37: 契約書等を決裁文書に添付する事
C38: (16) | D38: 個人情報が含まれる場合、個人情報の利用、管理などに十分な配慮がなされている
C39: (17) | D39: 広告に含まれる実験データや事例について、サンプル化・匿名化がなされている
C40: 【TVCMの場合】
C41: 対象の場合は以下チェック後、広報部門へご連絡ください
C42: (18) | D42: 文字表示（特に注釈類を含むもの）の露出秒数が2秒以上となっている | L42: FALSE
C43: (19) | D43: 文字数が1行に30文字※以内で2行以内となっている ※記号はカウントする、スペースはカウントしない
C44: (20) | D44: 注釈が3行以上にわたる場合は、訴求ポイント等注釈以外の文字も含めて視聴者が通常の見方で読み切ることができる秒数（最低3秒以上）を個別具体的に計測する等して十分に確保されている
C45: 【商品・サービスに関する広告の場合】
C46: 対象の場合は以下をチェックしてください
C47: (21) | D47: 品質、規格等を訴求する際、「安全」、「完全」、「万全」等、安全性・完全性を示す広告表示を使用していない
C48: (22) | D48: 世に出てから6か月以上経過した商品・サービスについて、「新登場」等の語を用いていない（広告期間中含む）
C49: 【NTTの研究所、研究技術に関する広告の場合】
C50: 対象の場合は以下をチェックしてください
C51: (23) | D51: 【持株会社のみ対象】 特定の1社専用の技術であるような排他的な表現にはなっていない（基盤的であることが認識できる） | L51: FALSE
C52: (24) | D52: 【持株会社のみ対象】 特定の事業会社やそのサービス等のプロモーション動画と受け取られるような表現になっていない
C53: (25) | D53: 【持株会社及び対象の事業会社対象】 他者と連携する取組み（共同研究・共同実験等）に基づく内容が含まれる場合、他社成果とNTT成果が区別されている（あるいはNTT成果のみの内容にとどめた内容で制作している）、また、他社成果内容も含め広告される場合に他社との間に契約その他の制約がない
C54: (26) | D54: 【持株会社及び対象の事業会社対象】 研究開発フェーズを踏まえ、（そうではないのに）すぐに使えるように過度の期待を持たせるような過度な表現にはなっていない
C55: (27) | D55: 【持株会社及び対象の事業会社対象】 一般公開できる内容である（守秘すべき会社技術/ノウハウ/報道発表前の内容（NDA等により守秘が必要な他社情報を含む）/特許出願のうち公開前の秘密情報を含んでいない）
C56: (28) | D56: 【持株会社及び対象の事業会社対象】 研究成果の背景として、従来技術の課題や社会で問題となっている事柄を示す場合、過度に不安をあおるような内容になっていない
C57: (29) | D57: 【持株会社及び対象の事業会社対象】 お客さまの声を掲載する際、実際の発言内容にとどめ、発言の時期・研究技術等の導入時期・効果はお客さまにより異なる旨を明示している
B59: 2. 景品表示法関連
C60: 項番 | D60: 内容 | E60: はい | F60: いいえ | G60: 対象外 | H60: 補足・備考
C61: (1) | D61: 商品またはサービスの仕様・キャンペーン内容などを訴求する場合、条件や例外事項等があれば適切に表示し、 実際より優良又は有利なものであるという誤認を招かない広告になっている
C62: (2) | D62: 過去の自社もしくは競合他社との比較をした広告表示、または No.1 表示※を含む広告表示がある場合、比較方法が公正で、範囲や表示の根拠となる調査の対象となった期間・時点が明瞭に表示されており、明確な根拠がある ※No.1 表示： 「No1」、「第一位」、「トップ」、「日本一」、「業界初」、「日本初」、「世界初」等の強調表示を指す | J62: FALSE | K62: FALSE
C63: (3) | D63: 景品表示法に従って、広告内容は適正に表示されており、比較広告で主張する内容に関する客観的に実証された根拠を確認している | J63: FALSE
C64: (4) | D64: 打消し表示（注釈）について、以下を満たしている - 一般消費者の不利益となる事実について打消し表示している - 打消し表示（注釈）の内容が、一般消費者にとって理解しやすい内容となっている - 打消し表示（注釈）の表示が、強調表示に近接した場所（直下、真横等）に一体の訴求として見えるように記載されている（別のページとなっていない） - 打消し表示（注釈）に用いる小さい文字のサイズは、強調する文字に対して7分の1以上となっている - Webページの場合、原則、強調表示からスクロールをしなくても表示される場所に表示している | J64: FALSE | K64: FALSE | L64: FALSE
C65: (5) | D65: リンク先にサービスの内容、取引条件について重要な情報を表示する場合、以下の項目全て満たしている - リンクの文字列に、リンク先に何が表示されているかが明確に分かる具体的な表現が用いられている - リンクの文字列がリンク先の情報に関連する情報の近くに表示されている | J65: FALSE | K65: FALSE | L65: FALSE
C66: (6) | D66: [不実証広告規制] 下記についての確認を行い、対応ができている ・表示内容が客観的に実証された内容のものである（次のいずれかに該当するもの） - 試験・調査によって得られた結果 - 専門家、専門家団体もしくは専門機関の見解または学術文献 ・表示された効果、性能と根拠資料によって実証された内容が適切に対応している ・広告表示審査時に当該根拠資料を併せて保管、提出している
C67: 【キャンペーンを実施する場合】
C68: 対象の場合は以下をチェックしてください。
C69: (7) | D69: 下記観点で、キャンペーン内容が正しく記載されている ①対象の特典を正しく記載していること NG例：特典がdポイント付与など現金でない場合に、「キャッシュバック」と表現を使っている。 ② 特典を受けるための条件・制約等を記載していること NG例：抽選なのに、抽選である旨の明記がない ：事前エントリー、アカウント連携、指定商品の購入、指定店舗での購入といった条件があるのに、 その記載がない。 ③②の記載を確実に認識できるよう、位置・サイズ等を考慮して記載していること NG例：条件・制約は記載しているが、小さい文字サイズや目立たない場所・色で記載している
C70: (8) | D70: 下記についての確認を行い、対応ができている ・「”期間限定”である旨を強調する表示」をしている場合、当該施策は１回限りの（延長の可能性もない）施策である ・施策期間を延長する場合（延長する可能性がある場合も含む）、「”期間限定”である旨を強調する表示」をしていない。また、注釈部分に申込受付期間等を表示し（申込受付期間を強調して表示せず）、かつ期間が延長される可能性がある旨を明記している（例：※期間は延長する場合があります。） ・「”期間限定”である旨を強調する表示」をした前回キャンペーンと同一のキャンペーン（一般消費者が明らかに違うキャンペーンであると認識できないものをいう。）を再度実施する場合には、最低２ヶ月（前回キャンペーンが２ヶ月を超える場合は前回キャンペーンと同期間）以上の間隔を空けている
C71: 【価格表示がある場合】
C72: 対象の場合は以下をチェックしてください
C73: (9) | D73: [価格表示] 下記についての確認を行い、対応ができている ・実際より安い価格を表示していない ・表示価格以外に、商品・サービスを利用するにあたり別途必要となる費用について、適切に表示している（総額表示となっている） ・表示価格が適用される対象者について、適切に表示している ・10％の税込価格となっている ・具体的な金額で工事費を訴求した場合、下記注釈（2つ）を記載している（記載の金額以外に工事費が発生しないのであれば、下記注釈の記載は不要） ①「記載の工事費は代表的な料金です。」 ②「お客さまのご利用環境等によっては、その他工事費が別途必要となる場合があります。」 | H73: 事業者間取引の場合は税抜き表示可 | J73: FALSE | K73: FALSE | L73: FALSE
C74: (10) | D74: [二重価格表示] 下記についての確認を行い、対応ができている ・比較対照価格に用いる価格について、「実際と異なる表示」や「あいまいな表示」を行っていない ・銘柄、品質、規格等からみて同一ではない商品、サービスの価格を比較対照価格に用いていない ・過去の販売価格を比較対照価格とする場合、以下の①～③をすべて満たしている ①最近時（過去8週間）において、当該比較対照価格での販売期間が過半を占めている ②当該比較対照価格で販売されていた期間が通算して２週間以上である ③当該比較対照価格で販売された最後の日から２週間以上経過していない ・将来の販売価格を比較対照価格とする場合、将来の価格設定は確かなもの （ごく短期間のみ当該価格で販売するわけではない） となっている ・希望小売価格を比較対照価格とする二重価格表示となっていない | J74: FALSE | L74: FALSE
B76: 3. 知的財産権関連
C77: 項番 | D77: 内容 | E77: はい | F77: いいえ | G77: 対象外 | H77: 補足・備考
C78: (1) | D78: エキストラや一般の出演者がいる場合、書面をもって出演に関する留意事項を取り交わしている | J78: TRUE | K78: TRUE | L78: TRUE
C79: (2) | D79: 外国の国旗・紋章、国際機関の標章、赤十字の標章、通貨・郵便切手等、公益的性格を有する証票等を許可なく使用していない | J79: FALSE | K79: FALSE | L79: FALSE
C80: (3) | D80: 広告で使用する他者の権利※について、目的・用途・公開方法・使用期間等の条件において、権利者（またはJASRAC等管理団体）から使用許諾を得ている、もしくは、ガイドラインや他社が定めるルール等、使用許諾条件として権利者から提示されたレギュレーションに沿った運用がなされている ※他者の権利： 登場人物（タレント・エキストラ・一般人含む）の肖像権、登場する社名や商品・ロゴ等の商標権、特徴ある建物や工業デザインなどの意匠権、映像・画像・使用楽曲・歌詞・ナレーション音声等の著作権 等 ※参考： 特許情報プラットフォーム 簡易検索 https://www.j-platpat.inpit.go.jp/ | H80: 他者権利の許諾に関する証跡を決裁文書に添付する事 | J80: FALSE | K80: FALSE | L80: FALSE
C81: (4) | D81: 著作権フリーのコンテンツ（フリー素材掲載サイト等）は、著作権者が不明確であるため、使用していない | H81: 著作権の帰属が明示されており、有償/無償の許諾条件、責任の規定が明確である法人事業者が運営しているコンテンツは除く（疑義がある場合は知財部門に相談）
C82: (5) | D82: 広告内における自社/他社商標について、ガイドラインや他社が定めるルール等に記載した内容に従い適切に使用している 参考： 特許情報プラットフォーム 簡易検索 https://www.j-platpat.inpit.go.jp/ | J82: FALSE
C83: (6) | D83: 自社の技術が特許出願中であること等を表示する場合、 ・公開公報・特許公報が発行される前（未公開）の特許出願番号を書いていない ・特許登録前なのに、登録済特許であるような誤解を与える表示をしていない | J83: FALSE
C84: (7) | D84: 商標出願中など、未登録の商標については、（例）『「●●●」は、NTTテクノクロス株式会社の商標です。』という表現になっている ※商標登録済みの場合は、下記表現にて記載 （例）『「●●●」は、NTTテクノクロス株式会社の登録商標です。』
C85: (8) | D85: 広く認識されている他人の商品等と同一または類似の表示を使い、他社の製品・サービスとの混同の惹起や他社の商標権を侵害したり、著名性にフリーライドする目的を推認させるような記載や表現はないことを知財部門に事前に確認済である | H85: 使用する製品名については、必ず、知財部門や特許事務所調査後の使用とすること | J85: FALSE
C86: (9) | D86: 広告・宣伝する製品・サービスの商標出願は済んでいる
C87: (10) | D87: 他社の事例紹介・推薦については承諾を書面等でとっている
C88: (11) | D88: 新製品や既存製品の新機能追加の場合、他者特許権の侵害可能性について知財部門と相談済みである
C89: (12) | D89: 新しいアイデアについては特許出願について知財部門と相談済みである
C90: (13) | D90: 自社・他社の機密情報は記載されていない
C91: (14) | D91: 国内で開催される展示会である（又は）海外展示会の場合は知財輸出と相談済みである

Sheet (B)論文・書籍・技術解説用 _総括表
A1: 外部発表_広告表示チェックシート(論文・書籍・技術解説用） : 統括表
A3: 本シートは書き込みセル以外を保護（ロック）しています。補足内容などの記載が必要な場合は、「補足・注記事項」欄を使用して下さい。
A5: １．発表案件（本チェックシートでのチェック対象）
B7: 本項は、原稿作成者、発表予定者等、チェックを受ける者が記載すること
B8: 項 目 | D8: 内 容
B9: 発表タイトル | D9: claude codeのログにタイムスタンプをいれよう
B10: 発表の種類(*1) | D10: Webサイトへの記事投稿
C11: 国名 | D11: 日本
B12: 発表先 | C12: 組織名(*2) | D12: クラスメソッド株式会社
C13: 掲載誌名等(*3) | D13: Zenn
B14: 発表予定時期(*4) | D14: 46181
B15: 原稿作成者・発表者 | C15: 所属 | D15: SED
C16: 氏名 | D16: 上原潤二
B17: 他社共同発表者 | C17: 企業名 | D17: なし
C18: 共同発表とする経緯
B19: 発表の趣旨・目的 | D19: 当社所属社員＋当社の技術力アピール
B21: (*1) 論文、雑誌への記事投稿、セミナー講演、展示会出展など
B22: (*2) 学会名、出版元、展示会主催者など
B23: (*3) 掲載誌名・?年?月号、学会の研究会名／大会名、展示会名
B24: (*4) 雑誌等の発行予定日、セミナー開催日、展示会開催期間(開始日、終了日）
A26: ２． チェック実施 | C26: 原稿作成者／発表者によるチェックは無効とします。
B28: 項 目 | D28: 内 容
B29: チェックした対象物(*1) | D29: 発表原稿
B30: チェック実施日 | D30: 46160
B31: チェック実施者(*2) (チェック責任者) | C31: チェック実施範囲 | D31: Ａ項－Ｈ項（含む、Ｇ項）
C32: 所属 | D32: SED
C33: 職位
C34: 氏名
B35: 補足事項など
B37: (*1) 記載例；「・・・論文の草稿」、「〇〇セミナーでの発表草稿」等
B38: (*2) 事業部長等重要な組織の長又は、事業部長等重要な組織の長から指示された者がチェックを実施すること
A40: ３． チェック結果
B42: 個々のチェック結果について、以下の確認をします。
B43: チェック結果 | D43: 対 応
B44: □ | C44: チェックがされていない項目です。■、◆、▼になるようチェックをして下さい。
B45: ◆ | C45: 添付資料の添付、又は、決裁文書への特記が必要とされるチェック結果です。指示事項に従って下さい。
B46: ■又は▼ | C46: 特に、リスク要因は無いと判断されます。
C48: 注 「チェック結果」欄は、「個別チェック」シートでの結果が自動反映されます。
A49: 項 目 | C49: チェック結果 （注） | D49: チェック事項概要 | E49: 指示事項
A50: Ａ 他社情報保護 | E50: -
B51: Ａ１ | C51: ='(B)論文・書籍・技術解説用_個別確認'!A9 -> ■ | D51: 他社機密情報の記載 | E51: ='(B)論文・書籍・技術解説用_個別確認'!E9 -> -
B52: Ａ２ | C52: ='(B)論文・書籍・技術解説用_個別確認'!A12 -> ■ | D52: 顧客システムの構成記載 | E52: ='(B)論文・書籍・技術解説用_個別確認'!E12 -> -
A53: Ｂ 自社情報保護 | E53: -
B54: Ｂ１ | C54: ='(B)論文・書籍・技術解説用_個別確認'!A19 -> ■ | D54: 当社機密情報の記載 | E54: ='(B)論文・書籍・技術解説用_個別確認'!E19 -> -
B55: Ｂ２ | C55: ='(B)論文・書籍・技術解説用_個別確認'!A22 -> ◆ | D55: 未公開技術の権利取得 | E55: ='(B)論文・書籍・技術解説用_個別確認'!E22 -> 技術内容の公表ではない／公知情報である等、特許出願予定の無いことを決裁文書に記載してください。
A56: Ｃ 公表後の権利帰属 | E56: -
B57: Ｃ１ | C57: ='(B)論文・書籍・技術解説用_個別確認'!A29 -> ■ | D57: 公表後の著作権帰属先 | E57: ='(B)論文・書籍・技術解説用_個別確認'!E29 -> -
A58: Ｄ 他社権利の侵害防止 | E58: -
B59: Ｄ１ | C59: ='(B)論文・書籍・技術解説用_個別確認'!A36 -> ▼ | D59: 他社(者)著作物の利用 | E59: ='(B)論文・書籍・技術解説用_個別確認'!E36 -> -
B60: Ｄ２ | C60: ='(B)論文・書籍・技術解説用_個別確認'!A40 -> ◆ | D60: 引用 | E60: ='(B)論文・書籍・技術解説用_個別確認'!E40 -> 引用チェックシートを添付して下さい。
B61: Ｄ３ | C61: ='(B)論文・書籍・技術解説用_個別確認'!A44 -> ▼ | D61: 改変利用 | E61: ='(B)論文・書籍・技術解説用_個別確認'!E44 -> Ｄ３項チェック不要です。
A62: Ｅ 公表の形態 | E62: -
B63: Ｅ１ | C63: ='(B)論文・書籍・技術解説用_個別確認'!A51 -> ◆ | D63: 職務著作(個人名の記載） | E63: ='(B)論文・書籍・技術解説用_個別確認'!E51 -> (ｱ)欄に個人名記載の理由を記入して下さい（リストを選択）
E64: =[1]個別確認!D55
B65: Ｅ２ | C65: ='(B)論文・書籍・技術解説用_個別確認'!A56 -> ■ | D65: 社名表記 | E65: ='(B)論文・書籍・技術解説用_個別確認'!E56 -> -
B66: Ｅ３ | C66: ='(B)論文・書籍・技術解説用_個別確認'!A60 -> ■ | D66: 自社商標表記 | E66: ='(B)論文・書籍・技術解説用_個別確認'!E60 -> -
B67: Ｅ４ | C67: ='(B)論文・書籍・技術解説用_個別確認'!A64 -> ■ | D67: 他社商標表記 | E67: ='(B)論文・書籍・技術解説用_個別確認'!E64 -> -
A68: Ｆ 個人情報保護 | E68: -
B69: Ｆ１ | C69: ='(B)論文・書籍・技術解説用_個別確認'!A75 -> ■ | D69: 個人情報 | E69: ='(B)論文・書籍・技術解説用_個別確認'!E75 -> -
A70: Ｇ 安全保障貿易管理 | E70: -
B71: Ｇ１ | C71: ='(B)論文・書籍・技術解説用_個別確認'!A84 -> ■ | D71: 公知性 | E71: ='(B)論文・書籍・技術解説用_個別確認'!E84 -> -
B72: G２ | C72: ='(B)論文・書籍・技術解説用_個別確認'!A87 -> ■ | D72: その他の取引有無 | E72: ='(B)論文・書籍・技術解説用_個別確認'!E87 -> -
A73: Ｈ 添付資料確認 | C73: ='(B)論文・書籍・技術解説用_個別確認'!A94 -> ■ | E73: -
A75: 補足・注記事項

Sheet (B)論文・書籍・技術解説用_個別確認
A1: 外部発表_広告標チェックシート(論文・書籍・技術解説用） ： 個別確認シート
B3: 確認方法 １)各項番の「チェック内容」について確認（Ｙｅｓ又はＮｏ）し、「サブチェック結果」欄の該当欄を、「●」を入力（メニュー選択）し、チェック内容欄に記載の「指示事項」に従って下さい。 ２）チェックに関して、補足などコメントがある場合は、右端のコメント欄に記載して下さい。 ３）「サブチェック結果」の選択により、「チェック結果」は自動的に設定されます。
A5: Ａ 他社情報保護（契約遵守）
B6: 他社から機密情報として受領した情報の扱いについて、契約/受領条件を満足していることを確認する
A8: チェック結果 | B8: 項番 | C8: サブチェック結果 | D8: チェック内容 | E8: 指示事項 | F8: コメント
A9: =IF(AND(C10="●",C11="●"),"error",IF(C10="●","■",IF(C11="●","◆","□"))) -> ■ | B9: Ａ１ | D9: 他社から機密情報として受領した営業情報／技術情報／ノウハウ情報が記載されているか？ Yes、Noいずれか該当する項の○を●にする。 | E9: =IF(AND(C10="●",C11="●"),"error【Yes/Noどちらかを●にしてください】",IF(C11="●","「他社からの承諾書」をチェックシートに添付してください。",IF(NOT(C10="●"),"A１項未チェックです。","-"))) -> -
B10: No | C10: ● | D10: 記載が無い。 ＝＞ Ａ２項のチェックに進む。
B11: Yes | C11: ○ | D11: 記載しているが、当該他社からの承諾文書を得ている（口頭での許諾では不足です。）。 ＝＞ Ａ２項のチェックに進む。
A12: =IF(AND(C13="●",C14="●"),"error",IF(C13="●","■",IF(C14="●","◆","□"))) -> ■ | B12: Ａ２ | D12: 当社が受注開発したシステムの機能・構成等を事例として記載するか？ Yes、Noいずれか該当する項の○を●にする。 | E12: =IF(AND(C13="●",C14="●"),"error【Yes/Noどちらかを●にしてください】",IF(C14="●","発注元からの承諾書をチェックシートに添付してください。",IF(NOT(C13="●"),"A2項未チェックです。","-"))) -> -
B13: No | C13: ● | D13: 記載していない（発注元との関係を特定できない内容、形態にしている場合も含む）。 ＝＞ Ｂ項のチェックに進む。
B14: Yes | C14: ○ | D14: 記載しているが、発注元から、内容、媒体、時期について文書による承諾を得ている（口頭での許諾では不足です。）。 ＝＞ Ｂ項のチェックに進む。
A16: Ｂ 自社情報保護
B17: 当社の機密情報(営業情報、技術情報、ノウハウ情報）が保護、権利確保できていること
A18: チェック結果 | B18: 項番 | C18: サブチェック結果 | D18: チェック内容 | E18: 指示事項 | F18: コメント
A19: =IF(AND(C20="●",C21="●"),"error",IF(C20="●","■",IF(C21="●","◆","□"))) -> ■ | B19: Ｂ１ | C19: 営業情報保護 | D19: 当社の未公開の営業情報を記載しているか？ No,Yes（承諾有）,Yes（承諾無し）いずれか該当する項の○を●にする。 | E19: =IF(AND(C20="●",C21="●"),"error【Yes/Noどちらかを●にしてください】",IF(C21="●","公開する理由/関連組織からの承諾を決裁文書に記載してください。",IF(NOT(C20="●"),"Ｂ１項未チェックです。","-"))) -> -
B20: No | C20: ● | D20: 未公開の営業情報を記載していない。 ＝＞ Ｂ２項のチェックに進む。
B21: Yes | C21: ○ | D21: 未公開の営業情報を記載しているが、公開する理由（報道発表、プロモーション等）があり、社内関連組織（当該営業情報の保有部門）から承諾を得ている。 ＝＞ Ｂ２項のチェックに進む。
A22: =IF(AND(C23="●",C24="●"),"error",IF(C23="●","■",IF(C24="●","◆","□"))) -> ◆ | B22: Ｂ２ | C22: ノウハウ保護 | D22: 技術情報、ノウハウ情報を公表する場合、当社権利として確保するために特許出願がされている、又は特許出願の手続きが進められているか？ Yes,Noいずれか該当する項の○を●にする。 | E22: =IF(AND(C23="●",C24="●"),"error【Yes/Noどちらかを●にしてください】",IF(C24="●","技術内容の公表ではない／公知情報である等、特許出願予定の無いことを決裁文書に記載してください。",IF(NOT(C23="●"),"Ｂ２項未チェックです。","-"))) -> 技術内容の公表ではない／公知情報である等、特許出願予定の無いことを決裁文書に記載してください。
B23: Yes | C23: ○ | D23: 発表予定内容について、特許出願済み／出願手続き／知財担当に相談している。 ＝＞ Ｃ項のチェックに進む。
B24: No | C24: ● | D24: 技術内容についての公表ではない、又は、公知の情報を寄せ集め(例えば、技術解説記事)なので、特許出願の予定無し。 ＝＞ Ｃ項のチェックに進む。
A26: Ｃ 公表後の権利帰属について
A28: チェック結果 | B28: 項番 | C28: サブチェック結果 | D28: チェック内容 | E28: 指示事項 | F28: コメント
A29: =IF(AND(C30="●",C31="●"),"error",IF(C30="●","■",IF(C31="●","◆","□"))) -> ■ | B29: Ｃ１ | C29: 著作権保護 | D29: 著作権は当社に留保される条件となっているか？ Yes、Noいずれか該当する項の○を●にする。 | E29: =IF(AND(C30="●",C31="●"),"error【Yes/Noどちらかを●にしてください】",IF(C31="●","著作権譲渡しても自社での使用/改変はできるなどの業務に支障の無い旨決裁文書に記載してください。",IF(NOT(C30="●"),"Ｃ１項未チェックです。","-"))) -> -
B30: Yes 著作権留保 | C30: ● | D30: 当社の著作物として公表する。 ⇒ Ｄ項のチェックに進む。
B31: No 著作権譲渡 | C31: ○ | D31: 著作権を主催者等に譲渡する条件とされているが、譲渡しても業務に支障はない。 （公表後、当社で他目的に複写、改変等が自由にできるなど） ⇒ Ｄ項のチェックに進む。
A33: Ｄ 他社権利の侵害防止
B34: 他人の著作物の一部を利用している場合のチェック事項
A35: チェック結果 | B35: 項番 | C35: サブチェック結果 | D35: チェック内容 | E35: 指示事項 | F35: コメント
A36: =IF(AND(C37="●",OR(C38="●",C39="●")),"error",IF(AND(C38="●",C39="●"),"error",IF(C37="●","■",IF(C38="●","▼",IF(C39="●","▼","□"))))) -> ▼ | B36: Ｄ１ | C36: 他社著作物 | D36: 他社(者)の著作物の全部又は一部を、そのまま或いは修正などして使用しているか？ 次の①、②、③の該当する項の○を●にする。 | E36: =IF(AND(C37="●",OR(C38="●",C39="●")),"error【①②③の何れかを●にしてください】",IF(AND(C38="●",C39="●"),"error【②③の何れかを●にしてください】",IF(C37="●","-",IF(C38="●","-",IF(C39="●","-","Ｄ１項未チェックです。"))))) -> -
B37: ① （不使用） | C37: ○ | D37: 他社(者)著作物を使用していない。 ＝＞ Ｅ項のチェックに進む。
B38: ② (改変無し使用) | C38: ● | D38: 他社(者)著作物を改変・修正せずに使用している。 ＝＞ Ｄ２項をチェックする。
B39: ③ (改変有り使用) | C39: ○ | D39: 他社(者)著作物を改変・修正して使用している。 ＝＞ Ｄ３項をチェックする。
A40: =IF(A36="■","▼",IF(AND(A36="▼",C39="●"),"▼",IF(AND(C41="●",C42="●"),"◆",IF(C41="●","◆",IF(C42="●","◆","□"))))) -> ◆ | B40: Ｄ２ | C40: 引用 | D40: 他社(者)著作物の全部／一部の表現を変更せずに利用している場合、適正に利用しているか？ 次の①、②の該当する項の○を●にする（複数の他者著作物が有る場合は①②共に●も可） | E40: =IF(A36="■","Ｄ２項チェック不要です。",IF(AND(A36="▼",C39="●"),"Ｄ２項チェック不要です。",IF(AND(C41="●",C42="●"),"「他社（者）著作物の使用許諾文書」および「引用チェックシート」を添付して下さい。使用許諾の許諾期間がある場合は公表する期間が許諾期間に含まれる事の証跡を示してください。",IF(C41="●","他社（者）著作物の使用許諾文書を添付して下さい。使用許諾の許諾期間がある場合は公表する期間が許諾期間に含まれる事の証跡を示してください。",IF(C42="●","引用チェックシートを添付して下さい。","Ｄ２項未チェックです。"))))) -> 引用チェックシートを添付して下さい。
B41: ① （許諾取得） | C41: ○ | D41: 利用した著作物の著作権者が承諾していることを示す文書がある【著作権帰属先（Ｃ１項結果）の説明もすること】。 ＝＞ Ｅ項のチェックに進む
B42: ② （引用） | C42: ● | D42: 著作権者から承諾を得ていないが、著作権法の「引用」の条件を満たしていることを、「引用チェックシート」にて確認できている。 ＝＞ Ｅ項のチェックに進む
D43: ここをクリックすると、『引用チェックシート』を取得できます。
A44: =IF(A36="■","▼",IF(AND(A36="▼",C38="●"),"▼",IF(AND(C45="●",C46="●"),"◆",IF(C45="●","◆",IF(C46="●","◆","□"))))) -> ▼ | B44: Ｄ３ | C44: 改変利用 | D44: 他社(者)著作物の全部／一部を変更・修正・改変・翻案して利用している場合、適正な利用か？ 次の①、②の該当する項の○を●にする。 | E44: =IF(A36="■","Ｄ３項チェック不要です。",IF(AND(A36="▼",C38="●"),"Ｄ３項チェック不要です。",IF(AND(C45="●",C46="●"),"「他社（者）著作物の使用許諾文書」および、知的財産担当と相談した結果、妥当な修正である旨が確認された文書を添付して下さい。",IF(C45="●","他社（者）著作物の使用許諾文書を添付して下さい。使用許諾の許諾期間がある場合は公表する期間が許諾期間に含まれる事の証跡を示してください。",IF(C46="●","知的財産担当と相談した結果、妥当な修正である旨が確認された文書を添付して下さい。","Ｄ３項未チェックです。"))))) -> Ｄ３項チェック不要です。
B45: ① （許諾取得） | C45: ○ | D45: 変更・修正・改変・翻案について、利用した著作物の著作権者が承諾していることを示す文書がある【著作権帰属先（Ｃ１項結果）の説明もすること】。 ＝＞ Ｅ項のチェックに進む
B46: ② （正当性） | C46: ○ | D46: 著作権者から承諾を得ていないが、知的財産担当により妥当な修正等である旨が確認されたことの文書がある。 ＝＞ Ｅ項のチェックに進む
A48: Ｅ 公表の形態
B49: 職務著作(著作権法15条)、CI/GI、商標表記関連
A50: チェック結果 | B50: 項番 | C50: サブチェック結果 | D50: チェック内容 | E50: 指示事項 | F50: コメント
A51: =IF(AND(C52="●",C53="●"),"error",IF(C52="●","■",IF(C53="●","◆","□"))) -> ◆ | B51: Ｅ１ | C51: 職務著作 | D51: 職務著作であることが明確か？（発表者、執筆者として個人（社員）名が記載されていないか？） Yes、Noいずれか該当する項の○を●にする。 | E51: =IF(AND(C52="●",C53="●"),"error【個人名の記載有り/無しの何れかに●をつけてください】",IF(C52="●","-",IF(C53="●","(ｱ)欄に個人名記載の理由を記入して下さい（リストを選択）","Ｅ１項未チェックです。"))) -> (ｱ)欄に個人名記載の理由を記入して下さい（リストを選択）
B52: Yes | C52: ○ | D52: 個人名の記載が無い（会社名での発表） ＝＞ Ｅ２項のチェックに進む。
B53: No | C53: ● | D53: 個人名の記載が有る（(ｱ)欄の理由を選択する） ＝＞ Ｅ２項のチェックに進む。
D54: 【注意】個人名のみで発表する場合、個人活動と会社業務の切り分けが十分に出来ていない可能性が高いと思われますので、慎重な対応をして下さい。
B55: (ｱ)個人名記載の理由 | D55: 当社および当社社員の技術力を示す好機となることから当社名および個人名を記載する
A56: =IF(AND(C58="●",C59="●"),"error",IF(C58="●","■","□")) -> ■ | B56: Ｅ２ | C56: 社名 | D56: 当社社名の表記は、CI/GIガイドライン(経企部HP参照)を満足しているか？ Yes、Noいずれか該当する項の○を●にする。 | E56: =IF(AND(C58="●",C59="●"),"error【YesかNoどちらかに●を付けて下さい】",IF(C58="●","-",IF(C59="●","ＣＩ/ＧＩガイドラインに従って社名標記を直してください。","Ｅ２項未チェックです。"))) -> -
D57: CI/GIガイドラインへのリンク
B58: Yes | C58: ● | D58: ガイドラインに沿った表記がされている。 ＝＞ Ｅ３項のチェックに進む
B59: No | C59: ○ | D59: ガイドラインに違反した表記がされている。
A60: =IF(AND(C62="●",C63="●"),"error",IF(C62="●","▼",IF(C63="●","■","□"))) -> ■ | B60: Ｅ３ | C60: 自社商標 | D60: 当社商品・サービス名の表記は、商標登録出願・登録している表記と一致しているか？ （出願登録内容は、知財HPの「商標出願・登録一覧」ファイルを参照）。 Yes、Noいずれか該当する項の○を●にする。 | E60: =IF(AND(C62="●",C63="●"),"error【Yes／Noとちらかに●を付けて下さい】",IF(C62="●","-",IF(C63="●","-","Ｅ３項未チェックです。"))) -> -
D61: 「商標登録一覧」（知財ＨＰ）へのリンク
B62: No | C62: ○ | D62: 当社商標は発表予定原稿に表記されていない。 ＝＞ Ｅ４項のチェックに進む。
B63: Yes | C63: ● | D63: 商標は、出願／登録と同じ表記がされている（変形しての使用がないこと）。 ＝＞ Ｅ４項のチェックに進む。
A64: =IF(AND(C65="●",OR(C67="●",C69="●",C70="●")),"error",IF(C65="●","■",IF(OR(AND(C69="●",C70="●"),AND(C67="●",C69="●",C70="●")),"◆",IF(AND(C67="●",C70="●"),"■","□")))) -> ■ | B64: Ｅ４ | C64: 他社商標 | D64: 他社の社名・商標の記載が有る場合、商標権者の許諾が不要な内容か？／必要に応じて許諾が必要か？／指定する商標の表記条件を満足しているか？／他社の社名・商品の信用を損なう、あるいは事実と反する内容になっていないか？ ⇒Yes、Noいずれか該当する項の○を●にする。 | E64: =IF(AND(C65="●",OR(C67="●",C69="●",C70="●")),"error【他社商標の表記有り/無しの何れかに●をつけてください】",IF(C65="●","-",IF(OR(AND(C69="●",C70="●"),AND(C67="●",C69="●",C70="●")),"他社商標の使用許諾の証拠を決裁文書に添付して下さい",IF(AND(C67="●",C70="●"),"-","Ｅ４項未チェックです。")))) -> -
B65: No 他社商標記載なし | C65: ○ | D65: 他社の社名や商標の記載がない ＝＞ Ｆ項のチェックに進む
B66: Yes 他社商標記載有り | D66: 他社の社名や商標の記載がある場合は、①②何れか（又は両方）で、かつ③を満たしている事を確認する。 （①②のどちらにも●が付かない場合は知財担当に相談すること）。 ＝＞ Ｆ項のチェックに進む
B67: ① | C67: ● | D67: 他社の社名や商標は技術名、又は客観的事実としてのみの記載である（当社製品の動作環境としての他社商標（製品）の記載、公開されている情報からの社名の引用等）
D68: 【注意】①の場合、他社のロゴの使用はＨＰ等で明示的に許諾されている場合を除き使用しない事。
B69: ② | C69: ○ | D69: 当社とのパートナーシップを想起させる内容で、他社商標（製品・サービス名）や他社の社名を記載しているが、当該商標・社名の記載の許諾を得ている（代理店契約等）。
B70: ③ | C70: ● | D70: ・他社の社名、商品の使用を損なう、あるいは事実と反する発表内容にはなっていない。 ・該当会社のHP等で指定された形式(TMやRの記載、文字間隔など)で表示されている。 ・ロゴ（②の場合）の場合許諾されている様態で表示されている。
A72: Ｆ 個人情報保護
A74: チェック結果 | B74: 項番 | C74: サブチェック結果 | D74: チェック内容 | E74: 指示事項 | F74: コメント
A75: =IF(AND(C78="●",C79="●"),"error",IF(C78="●","■",IF(C79="●","◆","□"))) -> ■ | B75: Ｆ１ | C75: 個人情報の記載 | D75: 発表資料に個人情報（注）が記載されているか？ Yes、Noいずれか該当する項の○を●にする。 | E75: =IF(AND(C78="●",C79="●"),"error【個人情報の記載無し/記載有りの何れかに●をつけてください】",IF(C78="●","-",IF(C79="●","個人情報記載に関する承諾文書を添付して下さい。","Ｆ１項未チェックです。"))) -> -
D76: 注；「個人情報」とは、生存する個人に関する情報であって、当該情報に含まれる氏名、生年月日その他の記述等により特定の個人を識別することができるもの（他の情報と容易に照合することができ、それにより特定の個人を識別することができることとなるものを含む。）を指します。（個人情報保護法における定義）
D77: TMSガイド「個人情報を第三者に提供する時の手続き」に則ってお進めください。
B78: Ｎｏ 記載なし | C78: ● | D78: 個人情報は記載されていない。 ＝＞ Ｇ項に進む。
B79: Ｙｅｓ 記載あり | C79: ○ | D79: 個人情報が記載されているが、当該個人若しくは当該個人情報の提供元から掲載を承諾することを示す文書がある。 ＝＞ Ｇ項に進む。
A81: Ｇ 安全保障貿易管理(役務取引)
A83: チェック結果 | B83: 項番 | C83: サブチェック結果 | D83: チェック内容 | E83: 指示事項 | F83: コメント
A84: =IF(AND(C85="●",C86="●"),"error",IF(C85="●","■",IF(C86="●","◆","□"))) -> ■ | B84: Ｇ１ | C84: 技術情報 公知性 | D84: 発表資料等は、公知にするための発表か？ ＝＞予定している発表が①②の該当する方を●にする。 | E84: =IF(AND(C85="●",C86="●"),"error【①か②どちらかに●を付けて下さい】",IF(C85="●","-",IF(C86="●","輸出審査の必要性の有無を決裁前に輸出管理担当に確認して下さい。","Ｇ１項未チェックです。"))) -> -
B85: ①公知にするための発表 | C85: ● | D85: 発表資料等は以下の何れかに該当する（該当するものが一つでもあれば●）。 ・出版予定書籍原稿、量販されてる／無償で制限なく配布される雑誌への投稿記事 ・誰でもが制限なくアクセスできるＨＰへの掲載記事 ・誰にでも制限なく配布するパンフレット、説明資料 ・誰にでも制限なく販売される装置/プログラム等に添付する説明資料（操作説明書等） ・学会発表用原稿、投稿論文 ・誰でもが制限なく参加できる展示会、セミナー等での講演用資料、展示パネル、配布資料 ・報道発表原稿 ＝＞Ｇ２項のチェックに進む
B86: ②それ以外 | C86: ○ | D86: 発表資料等は上記の何れにも該当しない ＝＞Ｇ２項のチェックに進む
A87: =IF(AND(C88="●",C89="●"),"error",IF(C89="●","■",IF(C88="●","◆","□"))) -> ■ | B87: Ｇ２ | C87: 貨物、プログラム、技術情報の取引有無 | D87: 外部発表する情報以外に、貨物・機器の海外持ち出し、プログラム・技術情報の非居住者への提供があるか？（海外展示会、国際学会講演等を想定） Yes、Noいずれか該当する項の○を●にする。 | E87: =IF(AND(C88="●",C89="●"),"error【YesかNoどちらかに●を付けて下さい】",IF(C89="●","-",IF(C88="●","輸出審査が必要です。輸出管理担当に相談して下さい。","Ｇ２項未チェックです。"))) -> -
B88: Yes | C88: ○ | D88: 貨物・機器の海外持ち出し、プログラム・技術情報の非居住者への提供がある。
B89: No | C89: ● | D89: 貨物・機器の海外持ち出し、プログラム・技術情報の非居住者への提供がない。
A91: Ｈ 添付資料確認
A93: チェック結果 | B93: 項番 | C93: サブチェック結果 | D93: チェック内容
A94: =IF(C94="●","■","□") -> ■ | B94: Ｈ | C94: ● | D94: Ａ項からＧ項で、チェック結果が、「◆」となっている項目の「指示事項」に記載の資料や特記事項が全て決裁文書に添付又は記載されていれば、サブチェック結果の○を●にする。
D95: 「◆」となっている項目は、統括表シートでも確認できます。

Sheet (A)(B)共通
A1: 外部発表_広告表示チェックシート（(A)(B)共通）
H2: 45962
H3: 広報部門、営業推進部門、知財・輸出部門
B6: 4. 人権関連
C7: 項番 | D7: 内容 | E7: はい | F7: いいえ | G7: 対象外 | H7: 補足・備考
C8: (1) | D8: 性別による役割の固定を行っていない | J8: FALSE | K8: FALSE
C9: (2) | D9: アンコンシャス・バイアスに注意し、ステレオタイプな描写を行っていない （彼、彼女など性別を特定できる表現ではなく、ご本人のお名前や、性別を特定しない呼び方に変更している）
C10: (3) | D10: 不自然な表現、不快な表現となっておらず、人体が見切れているように見えるイラストは利用していない （見切れている場合は壁や机など境界とセットで描いている）
C11: (4) | D11: 擬人化した動物の画を使用する場合、差別に通じる不快な表現となっていない
C12: (5) | D12: 思想・宗教・民族等のシンボルあるいはそれを模した図案などを使用していない
C13: (6) | D13: セクシャルハラスメントをはじめ、各種ハラスメントを想起させるイラスト・コンテンツとなるおそれはない
C14: (7) | D14: 海外において否定的なハンドサインを使っていない（サムズアップ、ピースサイン、OKサイン、特定の指を立てる、等）
C15: (8) | D15: 次の差別につながるおそれのある言葉の使用や表現はない ・部落差別 ・障がい者差別 ・性の差別（性的指向の差別・性自認の差別含む）・人種民族差別 ・職業差別 ・身体差別 ・エイズ差別 ・学歴差別 ・思想、信条に対する差別 ・地域差別 ・年齢差別 ・階級差別 ・外国人に対する差別
B17: 5. サステナビリティ関連
C18: 項番 | D18: 内容 | E18: はい | F18: いいえ | G18: 対象外 | H18: 補足・備考
C19: (1) | D19: 不都合な事実を伝えず、良い情報のみを伝達している内容になっていない （製品や企業活動の一部にのみ該当する環境訴求をもって、製品や企業活動全体に関する環境訴求を行っていない、 また、カーボン・オフセットのみに基づき、環境への悪影響が軽減されたなどと訴求していない）
C20: (2) | D20: 環境に関する訴求では、内容が国際社会での合意、科学的見解と矛盾していない （国連気候変動枠組条約締約国会議(COP)で採択される条約や、気候変動に関する政府間パネル(IPCC)の「1.5℃特別報告書」等の内容と矛盾していない）
C21: (3) | D21: 国や地域、時代や社会の状況を考慮した内容となっている （個人のリテラシーや国や社会の状況によって、具体的にどのような表現がウォッシュに相当するのかの判断基準は大きく異なるが、宗教や習慣、信条等に配慮した内容になっている）
C22: (4) | D22: 最新の「環境表示ガイドライン」※に沿って、下記の 5 つの基本項目に沿っている ① あいまいな表現や環境主張は行わないこと ② 環境主張の内容に説明文を付けること ③ 環境主張の検証に必要なデータ及び評価方法が提供可能であること ④ 製品又は工程における比較主張は LCA 評価、数値等により適切になされていること ⑤ 評価及び検証のための情報にアクセスが可能であること ※環境省「環境表示ガイドライン」 https://www.env.go.jp/policy/hozen/green/ecolabel/guideline/guideline.pdf
C23: (5) | D23: 【SDGsロゴを使用する場合】 国連のガイドライン※を守っている ※下記参照 ・ ポスター・ロゴ・アイコンおよびガイドライン（日本語：国際連合広報センター）： https://www.unic.or.jp/files/SDG_Guidelines_AUG_2019_Final_ja.pdf ・よく寄せられる質問（日本語：国際連合広報センター）： https://www.unic.or.jp/files/SDG_Branding_FAQ_Japanese.pdf

Sheet 改版履歴
B2: 年月日 | C2: 版数 | D2: 改版内容
B3: 2024/12/ | C3: 1 | D3: 持株広告審査制度に従ったチェック項目の見直し
B4: 2025/11/ | C4: 1.1 | D4: ・持株広告審査制度改正に従ったチェック項目の見直し ・知財財産権に対する確認項目の追加 ・補足事項の追記
